cz_nhm.py
cz_nhm-0.7.3.dist-info/licenses/LICENSE
cz_nhm-0.7.3.dist-info/METADATA
cz_nhm-0.7.3.dist-info/WHEEL
cz_nhm-0.7.3.dist-info/entry_points.txt
cz_nhm-0.7.3.dist-info/top_level.txt
cz_nhm-0.7.3.dist-info/RECORD
