Metadata-Version: 2.4
Name: cz_nhm
Version: 0.7.3
Summary: Commitizen config for the NHM, London
Author-email: Natural History Museum <data@nhm.ac.uk>
License: MIT
Project-URL: repository, https://github.com/NaturalHistoryMuseum/cz-nhm
Project-URL: changelog, https://github.com/NaturalHistoryMuseum/cz-nhm/blob/main/CHANGELOG.md
Classifier: License :: OSI Approved :: MIT License
Classifier: Programming Language :: Python :: 3
License-File: LICENSE
Requires-Dist: commitizen<5.0.0,>=4.7.2
Dynamic: license-file
